pingme/__init__.py
pingme/_modidx.py
pingme/api.py
pingme/core.py
pingme/hello_world.py
pingme/pingme_class.py
pingme/service.py
pingme/services.py
pingme/config/config.default.env
pingme/config/config.default.yaml
ssi_pingme-1.0.0.dist-info/LICENSE
ssi_pingme-1.0.0.dist-info/METADATA
ssi_pingme-1.0.0.dist-info/WHEEL
ssi_pingme-1.0.0.dist-info/entry_points.txt
ssi_pingme-1.0.0.dist-info/top_level.txt
ssi_pingme-1.0.0.dist-info/RECORD
