Metadata-Version: 2.2
Name: ssi_pingme
Version: 1.0.0
Summary: TODO
Home-page: https://github.com/$GIT_USER_NAME/pingme
Author: $GIT_USER_NAME
Author-email: kimleeng@gmail.com
License: MIT License
Keywords: nbdev jupyter notebook python
Classifier: Development Status :: 4 - Beta
Classifier: Intended Audience :: Developers
Classifier: Natural Language :: English
Classifier: Programming Language :: Python :: 3.10
Classifier: License :: OSI Approved :: MIT License
Requires-Python: >=3.10
License-File: LICENSE
Requires-Dist: fastcore
Requires-Dist: pydantic-settings
Requires-Dist: pydantic
Requires-Dist: uvicorn
Requires-Dist: python-dotenv
Requires-Dist: pandas
Requires-Dist: requests
Requires-Dist: fastapi
Requires-Dist: httpx
Requires-Dist: envyaml
Provides-Extra: dev
Requires-Dist: black; extra == "dev"
Dynamic: author
Dynamic: author-email
Dynamic: classifier
Dynamic: description
Dynamic: description-content-type
Dynamic: home-page
Dynamic: keywords
Dynamic: license
Dynamic: provides-extra
Dynamic: requires-dist
Dynamic: requires-python
Dynamic: summary
